pycertgen/__init__.py
pycertgen/__main__.py
pycertgen/generator.py
pycertgen/gui.py
pycertgen/ppt_manager.py
pycertgen/ppt_to_pdf.py
pycertgen-23.12.2.dist-info/METADATA
pycertgen-23.12.2.dist-info/WHEEL
pycertgen-23.12.2.dist-info/RECORD
