Metadata-Version: 2.1
Name: PyCertGen
Version: 23.12.2
Summary: Package for certificate generation
Home-page: https://github.com/EllianAbe/PyCertGen.git
Author: Ellian Abe
Author-email: ellian_abe@outlook.com
Requires-Python: >=3.6,<4.0
Classifier: Programming Language :: Python :: 3
Classifier: Programming Language :: Python :: 3.6
Classifier: Programming Language :: Python :: 3.7
Classifier: Programming Language :: Python :: 3.8
Classifier: Programming Language :: Python :: 3.9
Classifier: Programming Language :: Python :: 3.10
Classifier: Programming Language :: Python :: 3.11
Classifier: Programming Language :: Python :: 3.12
Requires-Dist: openpyxl (>=3.1.2)
Requires-Dist: pandas (>=2.1.2)
Requires-Dist: python-pptx (>=0.6.23)
